{"kind":"youtube#searchResult","etag":"e6LKMbETJAPeWIRCCLghJ6TTtfc","id":{"kind":"youtube#video","videoId":"Q0SY1Re2Ui8"},"snippet":{"publishedAt":"2011-10-20T20:30:52Z","channelId":"UCKZnppZawlJiqZPuZ4gfVCw","title":"COORDINATED UNIVERSAL TIME (UTC) via KHVH (Hawaii) April 1983","description":"One can still get UTC (Cooridinated Universal Time) via Googling it...and that display appears via old-school \"Nixie\" neon-vacuum ...","thumbnails":{"default":{"url":"https://i.ytimg.com/vi/Q0SY1Re2Ui8/default.jpg","width":120,"height":90},"medium":{"url":"https://i.ytimg.com/vi/Q0SY1Re2Ui8/mqdefault.jpg","width":320,"height":180},"high":{"url":"https://i.ytimg.com/vi/Q0SY1Re2Ui8/hqdefault.jpg","width":480,"height":360}},"channelTitle":"Ronald Vaughan","liveBroadcastContent":"none","publishTime":"2011-10-20T20:30:52Z"},"link":"https://www.youtube.com/watch?v=Q0SY1Re2Ui8","time":134,"duration":"PT2M14S","dimension":"2d","definition":"sd","caption":"false","licensedContent":false,"contentRating":{},"projection":"rectangular"}