{"kind":"youtube#searchResult","etag":"OzsEdDZdXUrfnTxkdjMndzeJhHY","id":{"kind":"youtube#video","videoId":"2EkS9OqmIs4"},"snippet":{"publishedAt":"2015-01-31T19:21:08Z","channelId":"UCjX58COleIWwvc0_e9r_oMA","title":"Ukrainian Opinion: Should the Russian language be given official status in Ukraine?","description":"Ukraine Today correspondent Sam Kearley asks Ukrainians a question: Should the Russian language be given official status in ...","thumbnails":{"default":{"url":"https://i.ytimg.com/vi/2EkS9OqmIs4/default.jpg","width":120,"height":90},"medium":{"url":"https://i.ytimg.com/vi/2EkS9OqmIs4/mqdefault.jpg","width":320,"height":180},"high":{"url":"https://i.ytimg.com/vi/2EkS9OqmIs4/hqdefault.jpg","width":480,"height":360}},"channelTitle":"UKRAINE TODAY","liveBroadcastContent":"none","publishTime":"2015-01-31T19:21:08Z"},"link":"https://www.youtube.com/watch?v=2EkS9OqmIs4","time":187,"duration":"PT3M7S","dimension":"2d","definition":"sd","caption":"false","licensedContent":true,"contentRating":{},"projection":"rectangular"}