{"kind":"youtube#searchResult","etag":"_u1rMNBMkSgyqHI2_qnSulYYD5c","id":{"kind":"youtube#video","videoId":"Y4zEPBZnokA"},"snippet":{"publishedAt":"2016-11-17T10:27:35Z","channelId":"UCHTK-2W11Vh1V4uwofOfR4w","title":"Ukraine parliament sacks prosecutor general","description":"(29 Mar 2016) Ukraine's parliament has accepted the resignation of the prosecutor general who has been accused of failing to ...","thumbnails":{"default":{"url":"https://i.ytimg.com/vi/Y4zEPBZnokA/default.jpg","width":120,"height":90},"medium":{"url":"https://i.ytimg.com/vi/Y4zEPBZnokA/mqdefault.jpg","width":320,"height":180},"high":{"url":"https://i.ytimg.com/vi/Y4zEPBZnokA/hqdefault.jpg","width":480,"height":360}},"channelTitle":"AP Archive","liveBroadcastContent":"none","publishTime":"2016-11-17T10:27:35Z"},"link":"https://www.youtube.com/watch?v=Y4zEPBZnokA","time":80,"duration":"PT1M20S","dimension":"2d","definition":"sd","caption":"false","licensedContent":false,"contentRating":{},"projection":"rectangular"}