{"kind":"youtube#searchResult","etag":"mnq6Tt5cw1ly8R7LsMj3rChd4P4","id":{"kind":"youtube#video","videoId":"0Uy144KFJoU"},"snippet":{"publishedAt":"2014-10-03T07:58:53Z","channelId":"UCV63FScHnShoobfaENC8R_Q","title":"Future enlargement of the European Union","description":"The future enlargement of the European Union is theoretically open to any European country which is democratic, operates a free ...","thumbnails":{"default":{"url":"https://i.ytimg.com/vi/0Uy144KFJoU/default.jpg","width":120,"height":90},"medium":{"url":"https://i.ytimg.com/vi/0Uy144KFJoU/mqdefault.jpg","width":320,"height":180},"high":{"url":"https://i.ytimg.com/vi/0Uy144KFJoU/hqdefault.jpg","width":480,"height":360}},"channelTitle":"Audiopedia","liveBroadcastContent":"none","publishTime":"2014-10-03T07:58:53Z"},"link":"https://www.youtube.com/watch?v=0Uy144KFJoU","time":5450,"duration":"PT1H30M50S","dimension":"2d","definition":"sd","caption":"false","licensedContent":false,"contentRating":{},"projection":"rectangular"}