{"kind":"youtube#searchResult","etag":"IFxukkXecG5dSEYWObteUN6PjFk","id":{"kind":"youtube#video","videoId":"40EihLq1aAo"},"snippet":{"publishedAt":"2011-03-01T19:07:34Z","channelId":"UC5O114-PQNYkurlTg6hekZw","title":"The War Against War - What is Peacekeeping?","description":"The War Against War is a documentary film about UN Peacekeeping operations. Part 1 of the documentary explains what ...","thumbnails":{"default":{"url":"https://i.ytimg.com/vi/40EihLq1aAo/default.jpg","width":120,"height":90},"medium":{"url":"https://i.ytimg.com/vi/40EihLq1aAo/mqdefault.jpg","width":320,"height":180},"high":{"url":"https://i.ytimg.com/vi/40EihLq1aAo/hqdefault.jpg","width":480,"height":360}},"channelTitle":"United Nations","liveBroadcastContent":"none","publishTime":"2011-03-01T19:07:34Z"},"link":"https://www.youtube.com/watch?v=40EihLq1aAo","time":264,"duration":"PT4M24S","dimension":"2d","definition":"sd","caption":"false","licensedContent":false,"contentRating":{},"projection":"rectangular"}