{"kind":"youtube#searchResult","etag":"1k6HNqH5yn_qOKIAfwq0t6nb_bk","id":{"kind":"youtube#video","videoId":"_2Q9zvjPCHA"},"snippet":{"publishedAt":"2014-06-23T19:21:44Z","channelId":"UCSrZ3UV4jOidv8ppoVuvW9Q","title":"Ukraine Foreign Minister sees EU membership within 10 years","description":"European foreign ministers will wait to see Russia's reaction to Ukrainian President Petro Poroshenko's peace plan before ...","thumbnails":{"default":{"url":"https://i.ytimg.com/vi/_2Q9zvjPCHA/default.jpg","width":120,"height":90},"medium":{"url":"https://i.ytimg.com/vi/_2Q9zvjPCHA/mqdefault.jpg","width":320,"height":180},"high":{"url":"https://i.ytimg.com/vi/_2Q9zvjPCHA/hqdefault.jpg","width":480,"height":360}},"channelTitle":"euronews","liveBroadcastContent":"none","publishTime":"2014-06-23T19:21:44Z"},"link":"https://www.youtube.com/watch?v=_2Q9zvjPCHA","time":166,"duration":"PT2M46S","dimension":"2d","definition":"sd","caption":"false","licensedContent":true,"contentRating":{},"projection":"rectangular"}